{"chunk_definitions":[{"chunk_id":"ckk7sxgsn9znq","chunk_label":"unnamed-chunk-1","document_id":"2A79811D","expansion_state":0,"options":{"engine":"r","include":false,"label":"unnamed-chunk-17","message":false,"warning":false},"row":18,"row_count":1,"visible":true},{"chunk_id":"ckxp7fi5ej490","chunk_label":"unnamed-chunk-2","document_id":"2A79811D","expansion_state":0,"options":{"engine":"r","include":false,"label":"unnamed-chunk-18","message":false,"warning":false},"row":24,"row_count":1,"visible":true},{"chunk_id":"c2dg3hnhh5j2v","chunk_label":"unnamed-chunk-3","document_id":null,"expansion_state":0,"options":{"engine":"r","label":"unnamed-chunk-20"},"row":69,"row_count":1,"visible":true},{"chunk_id":"csfdhr78c9l88","chunk_label":"unnamed-chunk-4","document_id":null,"expansion_state":0,"options":[],"row":151,"row_count":1,"visible":true},{"chunk_id":"codxcbk5respr","chunk_label":"unnamed-chunk-5","document_id":null,"expansion_state":0,"options":[],"row":178,"row_count":1,"visible":true},{"chunk_id":"ccbyh30tgvbyb","chunk_label":"unnamed-chunk-6","document_id":null,"expansion_state":0,"options":[],"row":205,"row_count":1,"visible":true},{"chunk_id":"cemcpkq1ne21d","chunk_label":"unnamed-chunk-7","document_id":null,"expansion_state":0,"options":[],"row":232,"row_count":1,"visible":true},{"chunk_id":"cka887vnw1zqs","chunk_label":"unnamed-chunk-8","document_id":"2A79811D","expansion_state":0,"options":{"engine":"r","include":false,"label":"unnamed-chunk-3","message":false,"warning":false},"row":242,"row_count":1,"visible":true},{"chunk_id":"ccevn79xftnnq","chunk_label":"unnamed-chunk-9","document_id":null,"expansion_state":0,"options":{"engine":"r","label":"unnamed-chunk-2"},"row":290,"row_count":1,"visible":true},{"chunk_id":"cczpvwp5ds9p3","chunk_label":"unnamed-chunk-10","document_id":null,"expansion_state":0,"options":[],"row":406,"row_count":1,"visible":true},{"chunk_id":"cjfx91jcnfw6q","chunk_label":"unnamed-chunk-11","document_id":null,"expansion_state":0,"options":[],"row":434,"row_count":1,"visible":true},{"chunk_id":"cgnej4xkl0sq7","chunk_label":"unnamed-chunk-12","document_id":null,"expansion_state":0,"options":[],"row":462,"row_count":1,"visible":true},{"chunk_id":"czk0aewydf1wf","chunk_label":"unnamed-chunk-13","document_id":null,"expansion_state":0,"options":[],"row":490,"row_count":1,"visible":true},{"chunk_id":"cm41ewgbka788","chunk_label":"unnamed-chunk-14","document_id":"2A79811D","expansion_state":0,"options":{"engine":"r","include":false,"label":"unnamed-chunk-2","message":false,"warning":false},"row":500,"row_count":1,"visible":true},{"chunk_id":"cyt109kwkng2c","chunk_label":"unnamed-chunk-15","document_id":null,"expansion_state":0,"options":[],"row":564,"row_count":1,"visible":true},{"chunk_id":"cpzlxp6uz4f5n","chunk_label":"unnamed-chunk-16","document_id":null,"expansion_state":0,"options":[],"row":592,"row_count":1,"visible":true},{"chunk_id":"cogfv80eixmch","chunk_label":"unnamed-chunk-17","document_id":null,"expansion_state":0,"options":[],"row":620,"row_count":1,"visible":true},{"chunk_id":"ca42msw265vs1","chunk_label":"unnamed-chunk-18","document_id":null,"expansion_state":0,"options":[],"row":648,"row_count":1,"visible":true},{"chunk_id":"crh75aamwde20","chunk_label":"unnamed-chunk-20","document_id":null,"expansion_state":0,"options":[],"row":796,"row_count":1,"visible":true},{"chunk_id":"c0ol5v08wj1t4","chunk_label":"unnamed-chunk-21","document_id":null,"expansion_state":0,"options":[],"row":824,"row_count":1,"visible":true},{"chunk_id":"clm7r97gumtdf","chunk_label":"unnamed-chunk-22","document_id":null,"expansion_state":0,"options":[],"row":852,"row_count":1,"visible":true},{"chunk_id":"ctxf5p28out45","chunk_label":"unnamed-chunk-23","document_id":null,"expansion_state":0,"options":[],"row":880,"row_count":1,"visible":true},{"chunk_id":"c33x0igokn9q6","chunk_label":"unnamed-chunk-24","document_id":null,"expansion_state":0,"options":{"engine":"r","label":"unnamed-chunk-1"},"row":904,"row_count":1,"visible":true}],"chunk_rendered_width":700,"doc_write_time":1549980681}